tracelite/__init__.py
tracelite/cli/main.py
tracelite/core/config.py
tracelite/core/filters.py
tracelite/core/models.py
tracelite/core/storage/base.py
tracelite/core/storage/sqlite.py
tracelite/middleware/django.py
tracelite/middleware/fastapi.py
tracelite/middleware/flask.py
tracelite/ui/viewer.py
tracelite-0.4.0.dist-info/METADATA
tracelite-0.4.0.dist-info/WHEEL
tracelite-0.4.0.dist-info/entry_points.txt
tracelite-0.4.0.dist-info/licenses/LICENSE
tracelite-0.4.0.dist-info/RECORD
