Metadata-Version: 2.4
Name: tracelite
Version: 0.4.0
Summary: Lightweight request & response tracing for your Flask, Django, or FastAPI dev server
Author-email: Yeongseon Choe <yeongseon.choe@gmail.com>
License-Expression: MIT
License-File: LICENSE
Requires-Python: <4.0,>=3.9
Requires-Dist: django>=4.2
Requires-Dist: fastapi>=0.115.12
Requires-Dist: flask>=3.0
Requires-Dist: httpx>=0.28.1
Requires-Dist: pydantic>=2.6
Requires-Dist: rich>=13.7
Requires-Dist: sqlalchemy>=2.0
Requires-Dist: starlette>=0.46.1
Requires-Dist: tomli>=2.0
Requires-Dist: typer>=0.15
Provides-Extra: dev
Requires-Dist: black>=25.1.0; extra == 'dev'
Requires-Dist: isort>=6.0.1; extra == 'dev'
Requires-Dist: pre-commit>=4.2.0; extra == 'dev'
Requires-Dist: pytest-cov>=5.0.0; extra == 'dev'
Requires-Dist: pytest>=8.3.5; extra == 'dev'
Requires-Dist: streamlit>=1.44.0; extra == 'dev'
Requires-Dist: tomli-w>=1.2.0; extra == 'dev'
